Oviz/__init__.py
Oviz/interface.py
Oviz/log_sys.py
Oviz/main.py
Oviz/Config/car.obj
Oviz/Config/color_map.json
Oviz/Config/default.png
Oviz/Config/init_canvas_cfg3d.json
Oviz/Config/layout_config.json
Oviz/Config/logo.pptx
Oviz/Config/menu_bar.json
Oviz/Config/oviz.png
Oviz/Config/status_bar.json
Oviz/Config/xshow.ico
Oviz/Config/colorful_car/00000.BMP
Oviz/Config/colorful_car/00001.BMP
Oviz/Config/colorful_car/00002.BMP
Oviz/Config/colorful_car/00003.BMP
Oviz/Config/colorful_car/00004.BMP
Oviz/Config/colorful_car/00005.BMP
Oviz/Config/colorful_car/00006.BMP
Oviz/Config/colorful_car/00007.BMP
Oviz/Config/colorful_car/00008.BMP
Oviz/Config/colorful_car/car.obj
Oviz/Config/colorful_car/spot.png
Oviz/Config/colorful_car/uisee.png
Oviz/Controller/__init__.py
Oviz/Controller/controller.py
Oviz/Controller/core.py
Oviz/MagicPipe/__init__.py
Oviz/MagicPipe/pipeline.py
Oviz/Model/__init__.py
Oviz/Model/model.py
Oviz/MsgManager/Exceptions.py
Oviz/MsgManager/README.md
Oviz/MsgManager/UltraDict.py
Oviz/MsgManager/__init__.py
Oviz/MsgManager/manager.py
Oviz/MsgManager/tcp_middleware.py
Oviz/MsgManager/udp_middleware.py
Oviz/MsgManager/ultra_middleware.py
Oviz/Resources/homepage.png
Oviz/Resources/show_image.jpg
Oviz/Resources/show_pointcloud.png
Oviz/Resources/show_voxel.png
Oviz/SmartParse/smart_parse.py
Oviz/Utils/__init__.py
Oviz/Utils/common_utils.py
Oviz/Utils/navi_state.py
Oviz/Utils/point_cloud_utils.py
Oviz/Utils/pypcd.py
Oviz/View/QxtSpanSlider.py
Oviz/View/box_marker.py
Oviz/View/custom_widget.py
Oviz/View/dock_view.py
Oviz/View/mov_obj.py
Oviz/View/view.py
Oviz/View/viz_core.py
oviz-0.1.5.dist-info/METADATA
oviz-0.1.5.dist-info/WHEEL
oviz-0.1.5.dist-info/entry_points.txt
oviz-0.1.5.dist-info/licenses/LICENSE
oviz-0.1.5.dist-info/RECORD
