Metadata-Version: 2.1
Name: Oviz
Version: 0.1.5
Summary: Oviz: A powerful visualization tool for all your data. See images, point clouds, and more. Your go-to choice for effortless visualization!
Project-URL: Homepage, https://github.com/xiaoqiang-cheng/Oviz
Author-email: xiaoqiang cheng <xiaoqiang.cheng@foxmail.com>
License:                     GNU GENERAL PUBLIC LICENSE
License-File: LICENSE
Classifier: License :: OSI Approved :: GNU General Public License (GPL)
Classifier: Operating System :: OS Independent
Classifier: Programming Language :: Python :: 3
Requires-Python: >=3.8
Requires-Dist: matplotlib>=3.4.3
Requires-Dist: numpy>=1.20.3
Requires-Dist: opencv-python>=4.7.0
Requires-Dist: pyside2>=5.15.2.1
Requires-Dist: python-lzf>=0.2.4
Requires-Dist: qdarkstyle>=3.0.2
Requires-Dist: scipy>=1.7.0
Requires-Dist: vispy>=0.12.0
